rgrader/__init__.py
rgrader/converter.py
rgrader/decorators.py
rgrader/drive.py
rgrader/exceptions.py
rgrader/globals.py
rgrader/grader.py
rgrader/services.py
rgrader/test_runner.py
rgrader/utils.py
rgrader/classroom/__init__.py
rgrader/classroom/commands.py
rgrader/classroom/connector.py
rgrader/classroom/model.py
rgrader/interactive/__init__.py
rgrader/interactive/constants.py
rgrader/interactive/interactive.py
rgrader/interactive/model.py
rgrader/interactive/panels.py
rgrader-1.5.22.dist-info/METADATA
rgrader-1.5.22.dist-info/WHEEL
rgrader-1.5.22.dist-info/entry_points.txt
rgrader-1.5.22.dist-info/top_level.txt
rgrader-1.5.22.dist-info/RECORD
