Metadata-Version: 2.1
Name: rgrader
Version: 1.5.22
Summary: A simple grader for python problems
Requires-Dist: inquirer ==3.3.0
Requires-Dist: google-api-core ==2.19.0
Requires-Dist: google-api-python-client ==2.131.0
Requires-Dist: google-auth ==2.29.0
Requires-Dist: google-auth-httplib2 ==0.2.0
Requires-Dist: google-auth-oauthlib ==1.2.0
Requires-Dist: googleapis-common-protos ==1.63.0
Requires-Dist: PyYAML ==6.0.1
Requires-Dist: pycurses ==0.0.25
Requires-Dist: pyperclip ==1.9.0
